easy_chrome/__init__.py
easy_chrome/driver.py
easy_chrome/element.py
easy_chrome/utils.py
easy_chrome/version.py
easy_chrome-2.0.3.dist-info/LICENSE
easy_chrome-2.0.3.dist-info/METADATA
easy_chrome-2.0.3.dist-info/WHEEL
easy_chrome-2.0.3.dist-info/top_level.txt
easy_chrome-2.0.3.dist-info/RECORD
