Metadata-Version: 2.1
Name: easy-chrome
Version: 2.0.3
Summary: selenium chrome extension with shortcuts to control driver and element
Author: VanCuong
Author-email: vuvancuong94@gmail.com
License: MIT
Project-URL: Source, https://github.com/wcuong/easy-chrome
Keywords: easy chrome chrome_driver selenium chromedriver
Classifier: Programming Language :: Python :: 3
Classifier: Intended Audience :: Developers
Classifier: License :: OSI Approved :: MIT License
Classifier: Operating System :: POSIX :: Linux
Classifier: Operating System :: Microsoft :: Windows
Classifier: Operating System :: MacOS
Requires-Python: >=3.9
License-File: LICENSE
Requires-Dist: selenium
Requires-Dist: webdriver-manager
